cocoAPI/__init__.py
cocoAPI/cocoAdvSearch.py
cocoAPI/cocoBase.py
cocoAPI/cocoGet.py
cocoAPI/cocoLog.py
cocoAPI/cocoPy.py
cocoAPI/cocoSearch.py
cocoAPI/default_search_requests.py
coconutpy_api-0.1.0.dist-info/METADATA
coconutpy_api-0.1.0.dist-info/WHEEL
coconutpy_api-0.1.0.dist-info/top_level.txt
coconutpy_api-0.1.0.dist-info/RECORD
