Metadata-Version: 2.4
Name: coconutPy-api
Version: 0.1.0
Summary: A Python wrapper for the COCONUT natural product database REST API.
Author-email: Kenneth Acosta <ikennethacosta@gmail.com>
License: MIT
Project-URL: Homepage, https://github.com/kenscripts/coconutPy
Project-URL: Issues, https://github.com/kenscripts/coconutPy/issues
Requires-Python: >=3.9
Requires-Dist: requests
